oneNeuron/Perceptron.py
oneNeuron/__init__.py
oneneuron_pkg_Vinayak_HUB1-0.0.7.dist-info/LICENSE
oneneuron_pkg_Vinayak_HUB1-0.0.7.dist-info/METADATA
oneneuron_pkg_Vinayak_HUB1-0.0.7.dist-info/WHEEL
oneneuron_pkg_Vinayak_HUB1-0.0.7.dist-info/top_level.txt
oneneuron_pkg_Vinayak_HUB1-0.0.7.dist-info/RECORD
