Metadata-Version: 2.1
Name: oneneuron-pkg-Vinayak-HUB1
Version: 0.0.7
Summary: A small package for perceptron
Home-page: https://github.com/Vinayak-HUB1/Oneneuron_pkg
Author: Vinayak-HUB1
Author-email: dumbre.vinayak@gmail.com
Project-URL: Bug Tracker, https://github.com/Vinayak-HUB1/Oneneuron_pkg/issues
Classifier: Programming Language :: Python :: 3
Classifier: License :: OSI Approved :: MIT License
Classifier: Operating System :: OS Independent
Requires-Python: >=3.6
License-File: LICENSE
Requires-Dist: numpy (==1.21.6)
Requires-Dist: pandas (==1.1.5)
Requires-Dist: joblib (==1.1.0)
